pacakegenow/__init__.py
pacakegenow/main.py
pacakegenow-0.1.1.dist-info/METADATA
pacakegenow-0.1.1.dist-info/WHEEL
pacakegenow-0.1.1.dist-info/entry_points.txt
pacakegenow-0.1.1.dist-info/top_level.txt
pacakegenow-0.1.1.dist-info/RECORD
